traffic_light.v
// traffic_light.v  (plain Verilog) - with pedestrian button
module traffic_light (
    input  wire clk,
    input  wire rst_n,      // active low reset
    input  wire ped_button, // pedestrian request (momentary)
    output reg [2:0] ns,   // ns = {red, yellow, green}
    output reg [2:0] ew,   // ew = {red, yellow, green}
    output reg ped_walk    // pedestrian "WALK" active during extended NS green
);

    // state encoding
    localparam S_NS_GREEN  = 3'd0;
    localparam S_NS_YEL    = 3'd1;
    localparam S_ALL_RED   = 3'd2;
    localparam S_EW_GREEN  = 3'd3;
    localparam S_EW_YEL    = 3'd4;
    localparam S_ALL_RED2  = 3'd5;

    reg [2:0] state;
    reg [2:0] next_state;
    reg [15:0] counter;        // main counter for durations
    reg ped_request;           // latched pedestrian request
    reg [15:0] ped_extend;     // pedestrian extend counter (counts down when serving)

    // durations (in clock ticks)
    localparam NS_GREEN_T = 16'd50; // base NS green
    localparam NS_YEL_T   = 16'd10;
    localparam ALL_RED_T  = 16'd5;
    localparam EW_GREEN_T = 16'd50;
    localparam EW_YEL_T   = 16'd10;
    localparam ALL_RED2_T = 16'd5;
    localparam PED_T      = 16'd20; // extra ticks to serve pedestrian

    // synchronous state + counters + ped request latch
    always @(posedge clk or negedge rst_n) begin
        if (!rst_n) begin
            state <= S_NS_GREEN;
            counter <= 16'd0;
            ped_request <= 1'b0;
            ped_extend <= 16'd0;
        end else begin
            // latch pedestrian request (edge or level doesn't matter; keep it simple)
            if (ped_button) ped_request <= 1'b1;

            // update main counter
            if (counter == 16'hFFFF) counter <= 16'd0;
            else counter <= counter + 16'd1;

            // if ped_extend active, count it down on each clock
            if (ped_extend != 16'd0) ped_extend <= ped_extend - 16'd1;

            state <= next_state;
        end
    end

    // next state logic
    always @(*) begin
        // by default, do not change state
        next_state = state;
        case (state)
            // In NS_GREEN, if ped_extend is active we hold extra time.
            S_NS_GREEN: begin
                // if we are in NS_GREEN and there's no ped_extend active, use base time
                if (ped_extend != 16'd0) begin
                    if (counter >= NS_GREEN_T + PED_T - 1) next_state = S_NS_YEL;
                end else begin
                    if (counter >= NS_GREEN_T - 1) next_state = S_NS_YEL;
                end
            end

            S_NS_YEL:   if (counter >= NS_YEL_T-1)   next_state = S_ALL_RED;
            S_ALL_RED:  if (counter >= ALL_RED_T-1)  next_state = S_EW_GREEN;
            S_EW_GREEN: if (counter >= EW_GREEN_T-1) next_state = S_EW_YEL;
            S_EW_YEL:   if (counter >= EW_YEL_T-1)   next_state = S_ALL_RED2;
            S_ALL_RED2: if (counter >= ALL_RED2_T-1) next_state = S_NS_GREEN;
            default: next_state = S_NS_GREEN;
        endcase
    end

    // When we enter NS_GREEN and a request exists, start ped_extend and clear the request
    // We'll implement this as a small combinational check and edge update in a synchronous block:
    // (To do it cleanly, detect when next_state is NS_GREEN and state != NS_GREEN to know an entry)
    reg entering_ns_green;
    always @(*) begin
        entering_ns_green = (next_state == S_NS_GREEN) && (state != S_NS_GREEN);
    end

    // But we need to actually set ped_extend and ped_walk inside a synchronous update.
    // We'll update ped_extend and ped_request in the posedge block above by checking entering_ns_green.
    // To do that, add another small sequential block (separate always) that uses entering_ns_green.
    always @(posedge clk or negedge rst_n) begin
        if (!rst_n) begin
            ped_extend <= 16'd0;
            ped_request <= 1'b0;
            // ped_request already handled above; this double-decl ensures init
        end else begin
            // When we just entered NS_GREEN, if there is a pending request, set ped_extend
            if (entering_ns_green && ped_request) begin
                ped_extend <= PED_T;
                ped_request <= 1'b0; // clear request, will be served now
            end
        end
    end

    // output logic (Moore)
    always @(*) begin
        // default outputs
        ns = 3'b100; // red,yel,green = {red,yel,green}
        ew = 3'b100;
        ped_walk = 1'b0;
        case (state)
            S_NS_GREEN: begin
                ns = 3'b001;
                ew = 3'b100;
                // ped_walk is high while ped_extend is counting (i.e., being served) OR during normal NS_GREEN when ped_extend>0
                if (ped_extend != 16'd0) ped_walk = 1'b1;
            end
            S_NS_YEL:   begin ns = 3'b010; ew = 3'b100; end
            S_ALL_RED:  begin ns = 3'b100; ew = 3'b100; end
            S_EW_GREEN: begin ns = 3'b100; ew = 3'b001; end
            S_EW_YEL:   begin ns = 3'b100; ew = 3'b010; end
            S_ALL_RED2: begin ns = 3'b100; ew = 3'b100; end
        endcase
    end

endmodule

tb_traffic.v
// tb_traffic.v - Testbench for traffic_light with pedestrian button
`timescale 1ns/1ps

module tb_traffic;
    reg clk;
    reg rst_n;
    reg ped_button;
    wire [2:0] ns;
    wire [2:0] ew;
    wire ped_walk;

    // instantiate DUT
    traffic_light dut (
        .clk(clk),
        .rst_n(rst_n),
        .ped_button(ped_button),
        .ns(ns),
        .ew(ew),
        .ped_walk(ped_walk)
    );

    // clock: 10ns period
    initial clk = 0;
    always #5 clk = ~clk;

    // waveform dump
    initial begin
        $dumpfile("dump.vcd");
        $dumpvars(0, tb_traffic);
        $dumpvars(0, dut);
    end

    // stimulus
    initial begin
        // reset
        ped_button = 0;
        rst_n = 0;
        #20;
        rst_n = 1;

        // wait a bit, then press ped button briefly (simulate a push)
        #180;        // at time 200ns total
        ped_button = 1;
        #20;
        ped_button = 0;

        // run long enough to see the request served in a future NS_GREEN
        #3000;

        $display("Simulation finished");
        $finish;
    end

endmodule

dump.vcd
$date
	Sat Dec 06 18:23:41 2025
$end
$version
	Icarus Verilog
$end
$timescale
	1ps
$end
$scope module tb_traffic $end
$var wire 1 ! ped_walk $end
$var wire 3 " ns [2:0] $end
$var wire 3 # ew [2:0] $end
$var reg 1 $ clk $end
$var reg 1 % ped_button $end
$var reg 1 & rst_n $end
$scope module dut $end
$var wire 1 $ clk $end
$var wire 1 % ped_button $end
$var wire 1 & rst_n $end
$var reg 16 ' counter [15:0] $end
$var reg 1 ( entering_ns_green $end
$var reg 3 ) ew [2:0] $end
$var reg 3 * next_state [2:0] $end
$var reg 3 + ns [2:0] $end
$var reg 16 , ped_extend [15:0] $end
$var reg 1 - ped_request $end
$var reg 1 ! ped_walk $end
$var reg 3 . state [2:0] $end
$upscope $end
$upscope $end
$scope module tb_traffic $end
$scope module dut $end
$upscope $end
$upscope $end
$enddefinitions $end
#0
$dumpvars
b0 .
0-
b0 ,
b1 +
b0 *
b100 )
0(
b0 '
0&
0%
0$
b100 #
b1 "
0!
$end
#5000
1$
#10000
0$
#15000
1$
#20000
0$
1&
#25000
b1 '
1$
#30000
0$
#35000
b10 '
1$
#40000
0$
#45000
b11 '
1$
#50000
0$
#55000
b100 '
1$
#60000
0$
#65000
b101 '
1$
#70000
0$
#75000
b110 '
1$
#80000
0$
#85000
b111 '
1$
#90000
0$
#95000
b1000 '
1$
#100000
0$
#105000
b1001 '
1$
#110000
0$
#115000
b1010 '
1$
#120000
0$
#125000
b1011 '
1$
#130000
0$
#135000
b1100 '
1$
#140000
0$
#145000
b1101 '
1$
#150000
0$
#155000
b1110 '
1$
#160000
0$
#165000
b1111 '
1$
#170000
0$
#175000
b10000 '
1$
#180000
0$
#185000
b10001 '
1$
#190000
0$
#195000
b10010 '
1$
#200000
0$
1%
#205000
b10011 '
1-
1$
#210000
0$
#215000
b10100 '
1$
#220000
0$
0%
#225000
b10101 '
1$
#230000
0$
#235000
b10110 '
1$
#240000
0$
#245000
b10111 '
1$
#250000
0$
#255000
b11000 '
1$
#260000
0$
#265000
b11001 '
1$
#270000
0$
#275000
b11010 '
1$
#280000
0$
#285000
b11011 '
1$
#290000
0$
#295000
b11100 '
1$
#300000
0$
#305000
b11101 '
1$
#310000
0$
#315000
b11110 '
1$
#320000
0$
#325000
b11111 '
1$
#330000
0$
#335000
b100000 '
1$
#340000
0$
#345000
b100001 '
1$
#350000
0$
#355000
b100010 '
1$
#360000
0$
#365000
b100011 '
1$
#370000
0$
#375000
b100100 '
1$
#380000
0$
#385000
b100101 '
1$
#390000
0$
#395000
b100110 '
1$
#400000
0$
#405000
b100111 '
1$
#410000
0$
#415000
b101000 '
1$
#420000
0$
#425000
b101001 '
1$
#430000
0$
#435000
b101010 '
1$
#440000
0$
#445000
b101011 '
1$
#450000
0$
#455000
b101100 '
1$
#460000
0$
#465000
b101101 '
1$
#470000
0$
#475000
b101110 '
1$
#480000
0$
#485000
b101111 '
1$
#490000
0$
#495000
b110000 '
1$
#500000
0$
#505000
b1 *
b110001 '
1$
#510000
0$
#515000
b10 "
b10 +
b10 *
b1 .
b110010 '
1$
#520000
0$
#525000
b100 "
b100 +
b11 *
b10 .
b110011 '
1$
#530000
0$
#535000
b1 #
b1 )
b100 *
b11 .
b110100 '
1$
#540000
0$
#545000
b10 #
b10 )
b101 *
b100 .
b110101 '
1$
#550000
0$
#555000
b100 #
b100 )
1(
b0 *
b101 .
b110110 '
1$
#560000
0$
#565000
1!
b1 "
b1 +
0(
0-
b10100 ,
b0 .
b110111 '
1$
#570000
0$
#575000
1!
b1 "
b1 +
b10011 ,
b111000 '
1$
#580000
0$
#585000
1!
b1 "
b1 +
b10010 ,
b111001 '
1$
#590000
0$
#595000
1!
b1 "
b1 +
b10001 ,
b111010 '
1$
#600000
0$
#605000
1!
b1 "
b1 +
b10000 ,
b111011 '
1$
#610000
0$
#615000
1!
b1 "
b1 +
b1111 ,
b111100 '
1$
#620000
0$
#625000
1!
b1 "
b1 +
b1110 ,
b111101 '
1$
#630000
0$
#635000
1!
b1 "
b1 +
b1101 ,
b111110 '
1$
#640000
0$
#645000
1!
b1 "
b1 +
b1100 ,
b111111 '
1$
#650000
0$
#655000
1!
b1 "
b1 +
b1011 ,
b1000000 '
1$
#660000
0$
#665000
1!
b1 "
b1 +
b1010 ,
b1000001 '
1$
#670000
0$
#675000
1!
b1 "
b1 +
b1001 ,
b1000010 '
1$
#680000
0$
#685000
1!
b1 "
b1 +
b1000 ,
b1000011 '
1$
#690000
0$
#695000
1!
b1 "
b1 +
b111 ,
b1000100 '
1$
#700000
0$
#705000
1!
b1 "
b1 +
b1 *
b110 ,
b1000101 '
1$
#710000
0$
#715000
0!
b10 "
b10 +
b10 *
b1 .
b101 ,
b1000110 '
1$
#720000
0$
#725000
b100 "
b100 +
b11 *
b10 .
b100 ,
b1000111 '
1$
#730000
0$
#735000
b1 #
b1 )
b100 *
b11 .
b11 ,
b1001000 '
1$
#740000
0$
#745000
b10 #
b10 )
b101 *
b100 .
b10 ,
b1001001 '
1$
#750000
0$
#755000
1(
b100 #
b100 )
b0 *
b101 .
b1 ,
b1001010 '
1$
#760000
0$
#765000
0(
b1 "
b1 +
b1 *
b0 .
b0 ,
b1001011 '
1$
#770000
0$
#775000
b10 "
b10 +
b10 *
b1 .
b1001100 '
1$
#780000
0$
#785000
b100 "
b100 +
b11 *
b10 .
b1001101 '
1$
#790000
0$
#795000
b1 #
b1 )
b100 *
b11 .
b1001110 '
1$
#800000
0$
#805000
b10 #
b10 )
b101 *
b100 .
b1001111 '
1$
#810000
0$
#815000
b100 #
b100 )
1(
b0 *
b101 .
b1010000 '
1$
#820000
0$
#825000
b1 "
b1 +
0(
b1 *
b0 .
b1010001 '
1$
#830000
0$
#835000
b10 "
b10 +
b10 *
b1 .
b1010010 '
1$
#840000
0$
#845000
b100 "
b100 +
b11 *
b10 .
b1010011 '
1$
#850000
0$
#855000
b1 #
b1 )
b100 *
b11 .
b1010100 '
1$
#860000
0$
#865000
b10 #
b10 )
b101 *
b100 .
b1010101 '
1$
#870000
0$
#875000
b100 #
b100 )
1(
b0 *
b101 .
b1010110 '
1$
#880000
0$
#885000
b1 "
b1 +
0(
b1 *
b0 .
b1010111 '
1$
#890000
0$
#895000
b10 "
b10 +
b10 *
b1 .
b1011000 '
1$
#900000
0$
#905000
b100 "
b100 +
b11 *
b10 .
b1011001 '
1$
#910000
0$
#915000
b1 #
b1 )
b100 *
b11 .
b1011010 '
1$
#920000
0$
#925000
b10 #
b10 )
b101 *
b100 .
b1011011 '
1$
#930000
0$
#935000
b100 #
b100 )
1(
b0 *
b101 .
b1011100 '
1$
#940000
0$
#945000
b1 "
b1 +
0(
b1 *
b0 .
b1011101 '
1$
#950000
0$
#955000
b10 "
b10 +
b10 *
b1 .
b1011110 '
1$
#960000
0$
#965000
b100 "
b100 +
b11 *
b10 .
b1011111 '
1$
#970000
0$
#975000
b1 #
b1 )
b100 *
b11 .
b1100000 '
1$
#980000
0$
#985000
b10 #
b10 )
b101 *
b100 .
b1100001 '
1$
#990000
0$
#995000
b100 #
b100 )
1(
b0 *
b101 .
b1100010 '
1$
#1000000
0$
#1005000
b1 "
b1 +
0(
b1 *
b0 .
b1100011 '
1$
#1010000
0$
#1015000
b10 "
b10 +
b10 *
b1 .
b1100100 '
1$
#1020000
0$
#1025000
b100 "
b100 +
b11 *
b10 .
b1100101 '
1$
#1030000
0$
#1035000
b1 #
b1 )
b100 *
b11 .
b1100110 '
1$
#1040000
0$
#1045000
b10 #
b10 )
b101 *
b100 .
b1100111 '
1$
#1050000
0$
#1055000
b100 #
b100 )
1(
b0 *
b101 .
b1101000 '
1$
#1060000
0$
#1065000
b1 "
b1 +
0(
b1 *
b0 .
b1101001 '
1$
#1070000
0$
#1075000
b10 "
b10 +
b10 *
b1 .
b1101010 '
1$
#1080000
0$
#1085000
b100 "
b100 +
b11 *
b10 .
b1101011 '
1$
#1090000
0$
#1095000
b1 #
b1 )
b100 *
b11 .
b1101100 '
1$
#1100000
0$
#1105000
b10 #
b10 )
b101 *
b100 .
b1101101 '
1$
#1110000
0$
#1115000
b100 #
b100 )
1(
b0 *
b101 .
b1101110 '
1$
#1120000
0$
#1125000
b1 "
b1 +
0(
b1 *
b0 .
b1101111 '
1$
#1130000
0$
#1135000
b10 "
b10 +
b10 *
b1 .
b1110000 '
1$
#1140000
0$
#1145000
b100 "
b100 +
b11 *
b10 .
b1110001 '
1$
#1150000
0$
#1155000
b1 #
b1 )
b100 *
b11 .
b1110010 '
1$
#1160000
0$
#1165000
b10 #
b10 )
b101 *
b100 .
b1110011 '
1$
#1170000
0$
#1175000
b100 #
b100 )
1(
b0 *
b101 .
b1110100 '
1$
#1180000
0$
#1185000
b1 "
b1 +
0(
b1 *
b0 .
b1110101 '
1$
#1190000
0$
#1195000
b10 "
b10 +
b10 *
b1 .
b1110110 '
1$
#1200000
0$
#1205000
b100 "
b100 +
b11 *
b10 .
b1110111 '
1$
#1210000
0$
#1215000
b1 #
b1 )
b100 *
b11 .
b1111000 '
1$
#1220000
0$
#1225000
b10 #
b10 )
b101 *
b100 .
b1111001 '
1$
#1230000
0$
#1235000
b100 #
b100 )
1(
b0 *
b101 .
b1111010 '
1$
#1240000
0$
#1245000
b1 "
b1 +
0(
b1 *
b0 .
b1111011 '
1$
#1250000
0$
#1255000
b10 "
b10 +
b10 *
b1 .
b1111100 '
1$
#1260000
0$
#1265000
b100 "
b100 +
b11 *
b10 .
b1111101 '
1$
#1270000
0$
#1275000
b1 #
b1 )
b100 *
b11 .
b1111110 '
1$
#1280000
0$
#1285000
b10 #
b10 )
b101 *
b100 .
b1111111 '
1$
#1290000
0$
#1295000
b100 #
b100 )
1(
b0 *
b101 .
b10000000 '
1$
#1300000
0$
#1305000
b1 "
b1 +
0(
b1 *
b0 .
b10000001 '
1$
#1310000
0$
#1315000
b10 "
b10 +
b10 *
b1 .
b10000010 '
1$
#1320000
0$
#1325000
b100 "
b100 +
b11 *
b10 .
b10000011 '
1$
#1330000
0$
#1335000
b1 #
b1 )
b100 *
b11 .
b10000100 '
1$
#1340000
0$
#1345000
b10 #
b10 )
b101 *
b100 .
b10000101 '
1$
#1350000
0$
#1355000
b100 #
b100 )
1(
b0 *
b101 .
b10000110 '
1$
#1360000
0$
#1365000
b1 "
b1 +
0(
b1 *
b0 .
b10000111 '
1$
#1370000
0$
#1375000
b10 "
b10 +
b10 *
b1 .
b10001000 '
1$
#1380000
0$
#1385000
b100 "
b100 +
b11 *
b10 .
b10001001 '
1$
#1390000
0$
#1395000
b1 #
b1 )
b100 *
b11 .
b10001010 '
1$
#1400000
0$
#1405000
b10 #
b10 )
b101 *
b100 .
b10001011 '
1$
#1410000
0$
#1415000
b100 #
b100 )
1(
b0 *
b101 .
b10001100 '
1$
#1420000
0$
#1425000
b1 "
b1 +
0(
b1 *
b0 .
b10001101 '
1$
#1430000
0$
#1435000
b10 "
b10 +
b10 *
b1 .
b10001110 '
1$
#1440000
0$
#1445000
b100 "
b100 +
b11 *
b10 .
b10001111 '
1$
#1450000
0$
#1455000
b1 #
b1 )
b100 *
b11 .
b10010000 '
1$
#1460000
0$
#1465000
b10 #
b10 )
b101 *
b100 .
b10010001 '
1$
#1470000
0$
#1475000
b100 #
b100 )
1(
b0 *
b101 .
b10010010 '
1$
#1480000
0$
#1485000
b1 "
b1 +
0(
b1 *
b0 .
b10010011 '
1$
#1490000
0$
#1495000
b10 "
b10 +
b10 *
b1 .
b10010100 '
1$
#1500000
0$
#1505000
b100 "
b100 +
b11 *
b10 .
b10010101 '
1$
#1510000
0$
#1515000
b1 #
b1 )
b100 *
b11 .
b10010110 '
1$
#1520000
0$
#1525000
b10 #
b10 )
b101 *
b100 .
b10010111 '
1$
#1530000
0$
#1535000
b100 #
b100 )
1(
b0 *
b101 .
b10011000 '
1$
#1540000
0$
#1545000
b1 "
b1 +
0(
b1 *
b0 .
b10011001 '
1$
#1550000
0$
#1555000
b10 "
b10 +
b10 *
b1 .
b10011010 '
1$
#1560000
0$
#1565000
b100 "
b100 +
b11 *
b10 .
b10011011 '
1$
#1570000
0$
#1575000
b1 #
b1 )
b100 *
b11 .
b10011100 '
1$
#1580000
0$
#1585000
b10 #
b10 )
b101 *
b100 .
b10011101 '
1$
#1590000
0$
#1595000
b100 #
b100 )
1(
b0 *
b101 .
b10011110 '
1$
#1600000
0$
#1605000
b1 "
b1 +
0(
b1 *
b0 .
b10011111 '
1$
#1610000
0$
#1615000
b10 "
b10 +
b10 *
b1 .
b10100000 '
1$
#1620000
0$
#1625000
b100 "
b100 +
b11 *
b10 .
b10100001 '
1$
#1630000
0$
#1635000
b1 #
b1 )
b100 *
b11 .
b10100010 '
1$
#1640000
0$
#1645000
b10 #
b10 )
b101 *
b100 .
b10100011 '
1$
#1650000
0$
#1655000
b100 #
b100 )
1(
b0 *
b101 .
b10100100 '
1$
#1660000
0$
#1665000
b1 "
b1 +
0(
b1 *
b0 .
b10100101 '
1$
#1670000
0$
#1675000
b10 "
b10 +
b10 *
b1 .
b10100110 '
1$
#1680000
0$
#1685000
b100 "
b100 +
b11 *
b10 .
b10100111 '
1$
#1690000
0$
#1695000
b1 #
b1 )
b100 *
b11 .
b10101000 '
1$
#1700000
0$
#1705000
b10 #
b10 )
b101 *
b100 .
b10101001 '
1$
#1710000
0$
#1715000
b100 #
b100 )
1(
b0 *
b101 .
b10101010 '
1$
#1720000
0$
#1725000
b1 "
b1 +
0(
b1 *
b0 .
b10101011 '
1$
#1730000
0$
#1735000
b10 "
b10 +
b10 *
b1 .
b10101100 '
1$
#1740000
0$
#1745000
b100 "
b100 +
b11 *
b10 .
b10101101 '
1$
#1750000
0$
#1755000
b1 #
b1 )
b100 *
b11 .
b10101110 '
1$
#1760000
0$
#1765000
b10 #
b10 )
b101 *
b100 .
b10101111 '
1$
#1770000
0$
#1775000
b100 #
b100 )
1(
b0 *
b101 .
b10110000 '
1$
#1780000
0$
#1785000
b1 "
b1 +
0(
b1 *
b0 .
b10110001 '
1$
#1790000
0$
#1795000
b10 "
b10 +
b10 *
b1 .
b10110010 '
1$
#1800000
0$
#1805000
b100 "
b100 +
b11 *
b10 .
b10110011 '
1$
#1810000
0$
#1815000
b1 #
b1 )
b100 *
b11 .
b10110100 '
1$
#1820000
0$
#1825000
b10 #
b10 )
b101 *
b100 .
b10110101 '
1$
#1830000
0$
#1835000
b100 #
b100 )
1(
b0 *
b101 .
b10110110 '
1$
#1840000
0$
#1845000
b1 "
b1 +
0(
b1 *
b0 .
b10110111 '
1$
#1850000
0$
#1855000
b10 "
b10 +
b10 *
b1 .
b10111000 '
1$
#1860000
0$
#1865000
b100 "
b100 +
b11 *
b10 .
b10111001 '
1$
#1870000
0$
#1875000
b1 #
b1 )
b100 *
b11 .
b10111010 '
1$
#1880000
0$
#1885000
b10 #
b10 )
b101 *
b100 .
b10111011 '
1$
#1890000
0$
#1895000
b100 #
b100 )
1(
b0 *
b101 .
b10111100 '
1$
#1900000
0$
#1905000
b1 "
b1 +
0(
b1 *
b0 .
b10111101 '
1$
#1910000
0$
#1915000
b10 "
b10 +
b10 *
b1 .
b10111110 '
1$
#1920000
0$
#1925000
b100 "
b100 +
b11 *
b10 .
b10111111 '
1$
#1930000
0$
#1935000
b1 #
b1 )
b100 *
b11 .
b11000000 '
1$
#1940000
0$
#1945000
b10 #
b10 )
b101 *
b100 .
b11000001 '
1$
#1950000
0$
#1955000
b100 #
b100 )
1(
b0 *
b101 .
b11000010 '
1$
#1960000
0$
#1965000
b1 "
b1 +
0(
b1 *
b0 .
b11000011 '
1$
#1970000
0$
#1975000
b10 "
b10 +
b10 *
b1 .
b11000100 '
1$
#1980000
0$
#1985000
b100 "
b100 +
b11 *
b10 .
b11000101 '
1$
#1990000
0$
#1995000
b1 #
b1 )
b100 *
b11 .
b11000110 '
1$
#2000000
0$
#2005000
b10 #
b10 )
b101 *
b100 .
b11000111 '
1$
#2010000
0$
#2015000
b100 #
b100 )
1(
b0 *
b101 .
b11001000 '
1$
#2020000
0$
#2025000
b1 "
b1 +
0(
b1 *
b0 .
b11001001 '
1$
#2030000
0$
#2035000
b10 "
b10 +
b10 *
b1 .
b11001010 '
1$
#2040000
0$
#2045000
b100 "
b100 +
b11 *
b10 .
b11001011 '
1$
#2050000
0$
#2055000
b1 #
b1 )
b100 *
b11 .
b11001100 '
1$
#2060000
0$
#2065000
b10 #
b10 )
b101 *
b100 .
b11001101 '
1$
#2070000
0$
#2075000
b100 #
b100 )
1(
b0 *
b101 .
b11001110 '
1$
#2080000
0$
#2085000
b1 "
b1 +
0(
b1 *
b0 .
b11001111 '
1$
#2090000
0$
#2095000
b10 "
b10 +
b10 *
b1 .
b11010000 '
1$
#2100000
0$
#2105000
b100 "
b100 +
b11 *
b10 .
b11010001 '
1$
#2110000
0$
#2115000
b1 #
b1 )
b100 *
b11 .
b11010010 '
1$
#2120000
0$
#2125000
b10 #
b10 )
b101 *
b100 .
b11010011 '
1$
#2130000
0$
#2135000
b100 #
b100 )
1(
b0 *
b101 .
b11010100 '
1$
#2140000
0$
#2145000
b1 "
b1 +
0(
b1 *
b0 .
b11010101 '
1$
#2150000
0$
#2155000
b10 "
b10 +
b10 *
b1 .
b11010110 '
1$
#2160000
0$
#2165000
b100 "
b100 +
b11 *
b10 .
b11010111 '
1$
#2170000
0$
#2175000
b1 #
b1 )
b100 *
b11 .
b11011000 '
1$
#2180000
0$
#2185000
b10 #
b10 )
b101 *
b100 .
b11011001 '
1$
#2190000
0$
#2195000
b100 #
b100 )
1(
b0 *
b101 .
b11011010 '
1$
#2200000
0$
#2205000
b1 "
b1 +
0(
b1 *
b0 .
b11011011 '
1$
#2210000
0$
#2215000
b10 "
b10 +
b10 *
b1 .
b11011100 '
1$
#2220000
0$
#2225000
b100 "
b100 +
b11 *
b10 .
b11011101 '
1$
#2230000
0$
#2235000
b1 #
b1 )
b100 *
b11 .
b11011110 '
1$
#2240000
0$
#2245000
b10 #
b10 )
b101 *
b100 .
b11011111 '
1$
#2250000
0$
#2255000
b100 #
b100 )
1(
b0 *
b101 .
b11100000 '
1$
#2260000
0$
#2265000
b1 "
b1 +
0(
b1 *
b0 .
b11100001 '
1$
#2270000
0$
#2275000
b10 "
b10 +
b10 *
b1 .
b11100010 '
1$
#2280000
0$
#2285000
b100 "
b100 +
b11 *
b10 .
b11100011 '
1$
#2290000
0$
#2295000
b1 #
b1 )
b100 *
b11 .
b11100100 '
1$
#2300000
0$
#2305000
b10 #
b10 )
b101 *
b100 .
b11100101 '
1$
#2310000
0$
#2315000
b100 #
b100 )
1(
b0 *
b101 .
b11100110 '
1$
#2320000
0$
#2325000
b1 "
b1 +
0(
b1 *
b0 .
b11100111 '
1$
#2330000
0$
#2335000
b10 "
b10 +
b10 *
b1 .
b11101000 '
1$
#2340000
0$
#2345000
b100 "
b100 +
b11 *
b10 .
b11101001 '
1$
#2350000
0$
#2355000
b1 #
b1 )
b100 *
b11 .
b11101010 '
1$
#2360000
0$
#2365000
b10 #
b10 )
b101 *
b100 .
b11101011 '
1$
#2370000
0$
#2375000
b100 #
b100 )
1(
b0 *
b101 .
b11101100 '
1$
#2380000
0$
#2385000
b1 "
b1 +
0(
b1 *
b0 .
b11101101 '
1$
#2390000
0$
#2395000
b10 "
b10 +
b10 *
b1 .
b11101110 '
1$
#2400000
0$
#2405000
b100 "
b100 +
b11 *
b10 .
b11101111 '
1$
#2410000
0$
#2415000
b1 #
b1 )
b100 *
b11 .
b11110000 '
1$
#2420000
0$
#2425000
b10 #
b10 )
b101 *
b100 .
b11110001 '
1$
#2430000
0$
#2435000
b100 #
b100 )
1(
b0 *
b101 .
b11110010 '
1$
#2440000
0$
#2445000
b1 "
b1 +
0(
b1 *
b0 .
b11110011 '
1$
#2450000
0$
#2455000
b10 "
b10 +
b10 *
b1 .
b11110100 '
1$
#2460000
0$
#2465000
b100 "
b100 +
b11 *
b10 .
b11110101 '
1$
#2470000
0$
#2475000
b1 #
b1 )
b100 *
b11 .
b11110110 '
1$
#2480000
0$
#2485000
b10 #
b10 )
b101 *
b100 .
b11110111 '
1$
#2490000
0$
#2495000
b100 #
b100 )
1(
b0 *
b101 .
b11111000 '
1$
#2500000
0$
#2505000
b1 "
b1 +
0(
b1 *
b0 .
b11111001 '
1$
#2510000
0$
#2515000
b10 "
b10 +
b10 *
b1 .
b11111010 '
1$
#2520000
0$
#2525000
b100 "
b100 +
b11 *
b10 .
b11111011 '
1$
#2530000
0$
#2535000
b1 #
b1 )
b100 *
b11 .
b11111100 '
1$
#2540000
0$
#2545000
b10 #
b10 )
b101 *
b100 .
b11111101 '
1$
#2550000
0$
#2555000
b100 #
b100 )
1(
b0 *
b101 .
b11111110 '
1$
#2560000
0$
#2565000
b1 "
b1 +
0(
b1 *
b0 .
b11111111 '
1$
#2570000
0$
#2575000
b10 "
b10 +
b10 *
b1 .
b100000000 '
1$
#2580000
0$
#2585000
b100 "
b100 +
b11 *
b10 .
b100000001 '
1$
#2590000
0$
#2595000
b1 #
b1 )
b100 *
b11 .
b100000010 '
1$
#2600000
0$
#2605000
b10 #
b10 )
b101 *
b100 .
b100000011 '
1$
#2610000
0$
#2615000
b100 #
b100 )
1(
b0 *
b101 .
b100000100 '
1$
#2620000
0$
#2625000
b1 "
b1 +
0(
b1 *
b0 .
b100000101 '
1$
#2630000
0$
#2635000
b10 "
b10 +
b10 *
b1 .
b100000110 '
1$
#2640000
0$
#2645000
b100 "
b100 +
b11 *
b10 .
b100000111 '
1$
#2650000
0$
#2655000
b1 #
b1 )
b100 *
b11 .
b100001000 '
1$
#2660000
0$
#2665000
b10 #
b10 )
b101 *
b100 .
b100001001 '
1$
#2670000
0$
#2675000
b100 #
b100 )
1(
b0 *
b101 .
b100001010 '
1$
#2680000
0$
#2685000
b1 "
b1 +
0(
b1 *
b0 .
b100001011 '
1$
#2690000
0$
#2695000
b10 "
b10 +
b10 *
b1 .
b100001100 '
1$
#2700000
0$
#2705000
b100 "
b100 +
b11 *
b10 .
b100001101 '
1$
#2710000
0$
#2715000
b1 #
b1 )
b100 *
b11 .
b100001110 '
1$
#2720000
0$
#2725000
b10 #
b10 )
b101 *
b100 .
b100001111 '
1$
#2730000
0$
#2735000
b100 #
b100 )
1(
b0 *
b101 .
b100010000 '
1$
#2740000
0$
#2745000
b1 "
b1 +
0(
b1 *
b0 .
b100010001 '
1$
#2750000
0$
#2755000
b10 "
b10 +
b10 *
b1 .
b100010010 '
1$
#2760000
0$
#2765000
b100 "
b100 +
b11 *
b10 .
b100010011 '
1$
#2770000
0$
#2775000
b1 #
b1 )
b100 *
b11 .
b100010100 '
1$
#2780000
0$
#2785000
b10 #
b10 )
b101 *
b100 .
b100010101 '
1$
#2790000
0$
#2795000
b100 #
b100 )
1(
b0 *
b101 .
b100010110 '
1$
#2800000
0$
#2805000
b1 "
b1 +
0(
b1 *
b0 .
b100010111 '
1$
#2810000
0$
#2815000
b10 "
b10 +
b10 *
b1 .
b100011000 '
1$
#2820000
0$
#2825000
b100 "
b100 +
b11 *
b10 .
b100011001 '
1$
#2830000
0$
#2835000
b1 #
b1 )
b100 *
b11 .
b100011010 '
1$
#2840000
0$
#2845000
b10 #
b10 )
b101 *
b100 .
b100011011 '
1$
#2850000
0$
#2855000
b100 #
b100 )
1(
b0 *
b101 .
b100011100 '
1$
#2860000
0$
#2865000
b1 "
b1 +
0(
b1 *
b0 .
b100011101 '
1$
#2870000
0$
#2875000
b10 "
b10 +
b10 *
b1 .
b100011110 '
1$
#2880000
0$
#2885000
b100 "
b100 +
b11 *
b10 .
b100011111 '
1$
#2890000
0$
#2895000
b1 #
b1 )
b100 *
b11 .
b100100000 '
1$
#2900000
0$
#2905000
b10 #
b10 )
b101 *
b100 .
b100100001 '
1$
#2910000
0$
#2915000
b100 #
b100 )
1(
b0 *
b101 .
b100100010 '
1$
#2920000
0$
#2925000
b1 "
b1 +
0(
b1 *
b0 .
b100100011 '
1$
#2930000
0$
#2935000
b10 "
b10 +
b10 *
b1 .
b100100100 '
1$
#2940000
0$
#2945000
b100 "
b100 +
b11 *
b10 .
b100100101 '
1$
#2950000
0$
#2955000
b1 #
b1 )
b100 *
b11 .
b100100110 '
1$
#2960000
0$
#2965000
b10 #
b10 )
b101 *
b100 .
b100100111 '
1$
#2970000
0$
#2975000
b100 #
b100 )
1(
b0 *
b101 .
b100101000 '
1$
#2980000
0$
#2985000
b1 "
b1 +
0(
b1 *
b0 .
b100101001 '
1$
#2990000
0$
